bunnyhopapi/__init__.py
bunnyhopapi/client_handler.py
bunnyhopapi/handlers.py
bunnyhopapi/models.py
bunnyhopapi/request.py
bunnyhopapi/response.py
bunnyhopapi/server.py
bunnyhopapi/swagger.py
bunnyhopapi/templates.py
bunnyhopapi/websocket.py
bunnyhopapi-1.5.0.dist-info/licenses/LICENSE
bunnyhopapi-1.5.0.dist-info/METADATA
bunnyhopapi-1.5.0.dist-info/WHEEL
bunnyhopapi-1.5.0.dist-info/top_level.txt
bunnyhopapi-1.5.0.dist-info/RECORD
