Metadata-Version: 2.4
Name: bunnyhopapi
Version: 1.5.0
Summary: BunnyHopApi is a lightweight and fast web framework designed to handle modern web development needs.
Home-page: https://github.com/rroblf01/bunnyhopapi
Author: Ricardo Robles Fernández
Author-email: ricardo.r.f@hotmail.com
License: MIT
Requires-Python: >=3.10
License-File: LICENSE
Requires-Dist: jinja2==3.1.6
Requires-Dist: pydantic==2.11.4
Requires-Dist: uvloop==0.21.0
Requires-Dist: watchdog==6.0.0
Provides-Extra: lint
Requires-Dist: ruff==0.11.4; extra == "lint"
Provides-Extra: dev
Requires-Dist: pytest==8.3.5; extra == "dev"
Requires-Dist: pytest-asyncio==0.26.0; extra == "dev"
Requires-Dist: pytest-cov==6.1.1; extra == "dev"
Dynamic: author
Dynamic: author-email
Dynamic: home-page
Dynamic: license-file
Dynamic: requires-python
